MANIFEST.in
requirements.txt
setup.py
allparts/__init__.py
allparts/__main__.py
allparts/s3merger.py
allparts.egg-info/PKG-INFO
allparts.egg-info/SOURCES.txt
allparts.egg-info/dependency_links.txt
allparts.egg-info/entry_points.txt
allparts.egg-info/requires.txt
allparts.egg-info/top_level.txt