Metadata-Version: 1.0
Name: allparts
Version: 0.1.0
Summary: A tool to merge all part files in an s3 bucket.
Home-page: https://github.com/Raynes/allparts
Author: Anthony Grimes
Author-email: i@raynes.me
License: MIT
Platform: UNKNOWN
